odoo10_addon_base_user_gravatar-10.0.1.0.1-py2.7-nspkg.pth
odoo/addons/base_user_gravatar/README.rst
odoo/addons/base_user_gravatar/__init__.py
odoo/addons/base_user_gravatar/__manifest__.py
odoo/addons/base_user_gravatar/i18n/ar.po
odoo/addons/base_user_gravatar/i18n/ca.po
odoo/addons/base_user_gravatar/i18n/da.po
odoo/addons/base_user_gravatar/i18n/de.po
odoo/addons/base_user_gravatar/i18n/el_GR.po
odoo/addons/base_user_gravatar/i18n/es.po
odoo/addons/base_user_gravatar/i18n/es_ES.po
odoo/addons/base_user_gravatar/i18n/fi.po
odoo/addons/base_user_gravatar/i18n/fr.po
odoo/addons/base_user_gravatar/i18n/fr_CH.po
odoo/addons/base_user_gravatar/i18n/fr_FR.po
odoo/addons/base_user_gravatar/i18n/hr.po
odoo/addons/base_user_gravatar/i18n/hr_HR.po
odoo/addons/base_user_gravatar/i18n/it.po
odoo/addons/base_user_gravatar/i18n/nl.po
odoo/addons/base_user_gravatar/i18n/nl_NL.po
odoo/addons/base_user_gravatar/i18n/pt.po
odoo/addons/base_user_gravatar/i18n/pt_BR.po
odoo/addons/base_user_gravatar/i18n/res_users_with_gravatar.pot
odoo/addons/base_user_gravatar/i18n/ro.po
odoo/addons/base_user_gravatar/i18n/sl.po
odoo/addons/base_user_gravatar/i18n/tr.po
odoo/addons/base_user_gravatar/i18n/tr_TR.po
odoo/addons/base_user_gravatar/i18n/zh_CN.po
odoo/addons/base_user_gravatar/models/__init__.py
odoo/addons/base_user_gravatar/models/res_users.py
odoo/addons/base_user_gravatar/static/description/icon.png
odoo/addons/base_user_gravatar/tests/__init__.py
odoo/addons/base_user_gravatar/tests/test_res_users.py
odoo/addons/base_user_gravatar/views/res_users_view.xml
odoo10_addon_base_user_gravatar-10.0.1.0.1.dist-info/DESCRIPTION.rst
odoo10_addon_base_user_gravatar-10.0.1.0.1.dist-info/METADATA
odoo10_addon_base_user_gravatar-10.0.1.0.1.dist-info/RECORD
odoo10_addon_base_user_gravatar-10.0.1.0.1.dist-info/WHEEL
odoo10_addon_base_user_gravatar-10.0.1.0.1.dist-info/metadata.json
odoo10_addon_base_user_gravatar-10.0.1.0.1.dist-info/namespace_packages.txt
odoo10_addon_base_user_gravatar-10.0.1.0.1.dist-info/top_level.txt
